README.md
setup.cfg
setup.py
cn_zipline/__init__.py
cn_zipline/__main__.py
cn_zipline/algorithm.py
cn_zipline/algorithm_live.py
cn_zipline/extension.py
cn_zipline/loader.py
cn_zipline.egg-info/PKG-INFO
cn_zipline.egg-info/SOURCES.txt
cn_zipline.egg-info/dependency_links.txt
cn_zipline.egg-info/entry_points.txt
cn_zipline.egg-info/requires.txt
cn_zipline.egg-info/top_level.txt
cn_zipline/bundles/__init__.py
cn_zipline/bundles/tdx_bundle.py
cn_zipline/examples/__init__.py
cn_zipline/examples/analyse.py
cn_zipline/examples/buyapple.py
cn_zipline/examples/live_strategy.py
cn_zipline/finance/__init__.py
cn_zipline/finance/controls.py
cn_zipline/gens/__init__.py
cn_zipline/gens/tdx_client.py
cn_zipline/gens/type.py
cn_zipline/gens/brokers/__init__.py
cn_zipline/gens/brokers/tdx_broker.py
cn_zipline/libs/__init__.py
cn_zipline/libs/tdx_api.pyd
cn_zipline/utils/__init__.py
cn_zipline/utils/register.py
cn_zipline/utils/run_algo.py
cn_zipline/utils/util.py