Metadata-Version: 1.0
Name: cn-zipline
Version: 0.38
Summary: china zipline bundles
Home-page: https://github.com/JaysonAlbert/cn_zipline
Author: Jie Wang
Author-email: 790930856@qq.com
License: UNKNOWN
Platform: UNKNOWN
